{"text": "\n₦ 13\n\nProtukoll 3 Nowembril 1886.\n\nKoos olid\n\npeawanem R. Priidemann\n\nI kõrwamees Jaan Madisson\n\nII \" R. Tomberg\n\n[järg]\n\nHans Leeberg oli kohtusse tulnud ja tunistas nüüd et tema selle sedulga, mis Jaan Roosmann Protkl. N 9 all sisse kaebanud olla küll warastanud. Tema pole seda küll oma käega hobuse pealt wõtnud, üks teine annud tema kätte ja tema müünud seda Jakob Mangmannile ilma et ütlenud et see warastud on. Tutta pole juba sell korral külles olnud.\n\nKohus mõistis: Jäeb poole et J. Roosmann kohtusse ei olnud tulnud.\n\nPeawanem R. Priidemann XXX\n\nJ. Madisson XXX\n\nR. Tomberg XXX\n\n\n", "meta": {}, "layers": [{"name": "flat_ner", "attributes": ["nertag"], "parent": null, "enveloping": null, "ambiguous": true, "serialisation_module": null, "meta": {}, "spans": [{"base_span": [56, 69], "annotations": [{"nertag": "PER"}]}, {"base_span": [83, 96], "annotations": [{"nertag": "PER"}]}, {"base_span": [103, 113], "annotations": [{"nertag": "PER"}]}, {"base_span": [123, 135], "annotations": [{"nertag": "PER"}]}, {"base_span": [200, 213], "annotations": [{"nertag": "PER"}]}, {"base_span": [365, 382], "annotations": [{"nertag": "PER"}]}, {"base_span": [419, 424], "annotations": [{"nertag": "PER"}]}, {"base_span": [491, 502], "annotations": [{"nertag": "PER"}]}, {"base_span": [539, 552], "annotations": [{"nertag": "PER"}]}, {"base_span": [558, 569], "annotations": [{"nertag": "PER"}]}, {"base_span": [575, 585], "annotations": [{"nertag": "PER"}]}]}]}