{"text": "Kusta Paabor ja tema nene endine Miina Kala tegid oma wahel järgmise leppingu:Miina annab oma maja ja maa s.o. 1/4 osa kõigest Räustawa talu krundist Ahjawallast Kustale, kes kui peremees ja tema (Miina) mees seal sees walitseb ja kelle omanduseks tema jääb selle eest peab aga Kusta Paabor ja lubab Miina esimse mehe lapsele Jaanile 100 rbl. 1895 aastal kohtu kätte hoiu alla maksma ja tütar Juulale Semmel 1 lehm ja 1 lammas ja 1 rõiwa luhwri ilma rõiwata kui sõsar täisealiseks saab wäljamaksma.Peale selle peab Kusta paabor weel oma ämma Marit auusaste ülewal pidama ja teda matma peale tema surma. Kusta peab Miina poega Jaani koolitama ja kaswatama niisama ka Juulat.Kusta Paabor &lt;allkiri&gt;Miina Paabor &lt;allkiri&gt;Et Kohus kokkuleppijaid pooli tunneb, tunnistabEesistuja a.s. J. Sikkut &lt;allkiri&gt;Kirjut: J Puusepp &lt;allkiri&gt;", "meta": {}, "layers": [{"name": "tokens", "attributes": [], "parent": null, "enveloping": null, "ambiguous": false, "serialisation_module": null, "meta": {}, "spans": [{"base_span": [0, 5], "annotations": [{}]}, {"base_span": [6, 12], "annotations": [{}]}, {"base_span": [13, 15], "annotations": [{}]}, {"base_span": [16, 20], "annotations": [{}]}, {"base_span": [21, 25], "annotations": [{}]}, {"base_span": [26, 32], "annotations": [{}]}, {"base_span": [33, 38], "annotations": [{}]}, {"base_span": [39, 43], "annotations": [{}]}, {"base_span": [44, 49], "annotations": [{}]}, {"base_span": [50, 53], "annotations": [{}]}, {"base_span": [54, 59], "annotations": [{}]}, {"base_span": [60, 68], "annotations": [{}]}, {"base_span": [69, 77], "annotations": [{}]}, {"base_span": [77, 78], "annotations": [{}]}, {"base_span": [78, 83], "annotations": [{}]}, {"base_span": [84, 89], "annotations": [{}]}, {"base_span": [90, 93], "annotations": [{}]}, {"base_span": [94, 98], "annotations": [{}]}, {"base_span": [99, 101], "annotations": [{}]}, {"base_span": [102, 105], "annotations": [{}]}, {"base_span": [106, 107], "annotations": [{}]}, {"base_span": [107, 108], "annotations": [{}]}, {"base_span": [108, 109], "annotations": [{}]}, {"base_span": [109, 110], "annotations": [{}]}, {"base_span": [111, 112], "annotations": [{}]}, {"base_span": [112, 113], "annotations": [{}]}, {"base_span": [113, 114], "annotations": [{}]}, {"base_span": [115, 118], "annotations": [{}]}, {"base_span": [119, 126], "annotations": [{}]}, {"base_span": [127, 135], "annotations": [{}]}, {"base_span": [136, 140], "annotations": [{}]}, {"base_span": [141, 149], "annotations": [{}]}, {"base_span": [150, 161], "annotations": [{}]}, {"base_span": [162, 169], "annotations": [{}]}, {"base_span": [169, 170], "annotations": [{}]}, {"base_span": [171, 174], "annotations": [{}]}, {"base_span": [175, 178], "annotations": [{}]}, {"base_span": [179, 187], "annotations": [{}]}, {"base_span": [188, 190], "annotations": [{}]}, {"base_span": [191, 195], "annotations": [{}]}, {"base_span": [196, 197], "annotations": [{}]}, {"base_span": [197, 202], "annotations": [{}]}, {"base_span": [202, 203], "annotations": [{}]}, {"base_span": [204, 208], "annotations": [{}]}, {"base_span": [209, 213], "annotations": [{}]}, {"base_span": [214, 218], "annotations": [{}]}, {"base_span": [219, 227], "annotations": [{}]}, {"base_span": [228, 230], "annotations": [{}]}, {"base_span": [231, 236], "annotations": [{}]}, {"base_span": [237, 247], "annotations": [{}]}, {"base_span": [248, 252], "annotations": [{}]}, {"base_span": [253, 257], "annotations": [{}]}, {"base_span": [258, 263], "annotations": [{}]}, {"base_span": [264, 268], "annotations": [{}]}, {"base_span": [269, 273], "annotations": [{}]}, {"base_span": [274, 277], "annotations": [{}]}, {"base_span": [278, 283], "annotations": [{}]}, {"base_span": [284, 290], "annotations": [{}]}, {"base_span": [291, 293], "annotations": [{}]}, {"base_span": [294, 299], "annotations": [{}]}, {"base_span": [300, 305], "annotations": [{}]}, {"base_span": [306, 312], "annotations": [{}]}, {"base_span": [313, 317], "annotations": [{}]}, {"base_span": [318, 325], "annotations": [{}]}, {"base_span": [326, 333], "annotations": [{}]}, {"base_span": [334, 337], "annotations": [{}]}, {"base_span": [338, 341], "annotations": [{}]}, {"base_span": [341, 342], "annotations": [{}]}, {"base_span": [343, 347], "annotations": [{}]}, {"base_span": [348, 354], "annotations": [{}]}, {"base_span": [355, 360], "annotations": [{}]}, {"base_span": [361, 366], "annotations": [{}]}, {"base_span": [367, 371], "annotations": [{}]}, {"base_span": [372, 376], "annotations": [{}]}, {"base_span": [377, 383], "annotations": [{}]}, {"base_span": [384, 386], "annotations": [{}]}, {"base_span": [387, 392], "annotations": [{}]}, {"base_span": [393, 400], "annotations": [{}]}, {"base_span": [401, 407], "annotations": [{}]}, {"base_span": [408, 409], "annotations": [{}]}, {"base_span": [410, 414], "annotations": [{}]}, {"base_span": [415, 417], "annotations": [{}]}, {"base_span": [418, 419], "annotations": [{}]}, {"base_span": [420, 426], "annotations": [{}]}, {"base_span": [427, 429], "annotations": [{}]}, {"base_span": [430, 431], "annotations": [{}]}, {"base_span": [432, 437], "annotations": [{}]}, {"base_span": [438, 444], "annotations": [{}]}, {"base_span": [445, 449], "annotations": [{}]}, {"base_span": [450, 457], "annotations": [{}]}, {"base_span": [458, 461], "annotations": [{}]}, {"base_span": [462, 467], "annotations": [{}]}, {"base_span": [468, 480], "annotations": [{}]}, {"base_span": [481, 485], "annotations": [{}]}, {"base_span": [486, 497], "annotations": [{}]}, {"base_span": [497, 498], "annotations": [{}]}, {"base_span": [498, 503], "annotations": [{}]}, {"base_span": [504, 509], "annotations": [{}]}, {"base_span": [510, 514], "annotations": [{}]}, {"base_span": [515, 520], "annotations": [{}]}, {"base_span": [521, 527], "annotations": [{}]}, {"base_span": [528, 532], "annotations": [{}]}, {"base_span": [533, 536], "annotations": [{}]}, {"base_span": [537, 541], "annotations": [{}]}, {"base_span": [542, 547], "annotations": [{}]}, {"base_span": [548, 556], "annotations": [{}]}, {"base_span": [557, 563], "annotations": [{}]}, {"base_span": [564, 570], "annotations": [{}]}, {"base_span": [571, 573], "annotations": [{}]}, {"base_span": [574, 578], "annotations": [{}]}, {"base_span": [579, 584], "annotations": [{}]}, {"base_span": [585, 590], "annotations": [{}]}, {"base_span": [591, 595], "annotations": [{}]}, {"base_span": [596, 601], "annotations": [{}]}, {"base_span": [601, 602], "annotations": [{}]}, {"base_span": [603, 608], "annotations": [{}]}, {"base_span": [609, 613], "annotations": [{}]}, {"base_span": [614, 619], "annotations": [{}]}, {"base_span": [620, 625], "annotations": [{}]}, {"base_span": [626, 631], "annotations": [{}]}, {"base_span": [632, 641], "annotations": [{}]}, {"base_span": [642, 644], "annotations": [{}]}, {"base_span": [645, 654], "annotations": [{}]}, {"base_span": [655, 662], "annotations": [{}]}, {"base_span": [663, 665], "annotations": [{}]}, {"base_span": [666, 672], "annotations": [{}]}, {"base_span": [672, 673], "annotations": [{}]}, {"base_span": [673, 678], "annotations": [{}]}, {"base_span": [679, 685], "annotations": [{}]}, {"base_span": [686, 687], "annotations": [{}]}, {"base_span": [687, 689], "annotations": [{}]}, {"base_span": [689, 690], "annotations": [{}]}, {"base_span": [690, 697], "annotations": [{}]}, {"base_span": [697, 698], "annotations": [{}]}, {"base_span": [698, 700], "annotations": [{}]}, {"base_span": [700, 701], "annotations": [{}]}, {"base_span": [701, 706], "annotations": [{}]}, {"base_span": [707, 713], "annotations": [{}]}, {"base_span": [714, 715], "annotations": [{}]}, {"base_span": [715, 717], "annotations": [{}]}, {"base_span": [717, 718], "annotations": [{}]}, {"base_span": [718, 725], "annotations": [{}]}, {"base_span": [725, 726], "annotations": [{}]}, {"base_span": [726, 728], "annotations": [{}]}, {"base_span": [728, 729], "annotations": [{}]}, {"base_span": [729, 731], "annotations": [{}]}, {"base_span": [732, 737], "annotations": [{}]}, {"base_span": [738, 752], "annotations": [{}]}, {"base_span": [753, 758], "annotations": [{}]}, {"base_span": [759, 765], "annotations": [{}]}, {"base_span": [765, 766], "annotations": [{}]}, {"base_span": [767, 785], "annotations": [{}]}, {"base_span": [786, 787], "annotations": [{}]}, {"base_span": [787, 788], "annotations": [{}]}, {"base_span": [788, 789], "annotations": [{}]}, {"base_span": [789, 790], "annotations": [{}]}, {"base_span": [791, 792], "annotations": [{}]}, {"base_span": [792, 793], "annotations": [{}]}, {"base_span": [794, 800], "annotations": [{}]}, {"base_span": [801, 802], "annotations": [{}]}, {"base_span": [802, 804], "annotations": [{}]}, {"base_span": [804, 805], "annotations": [{}]}, {"base_span": [805, 812], "annotations": [{}]}, {"base_span": [812, 813], "annotations": [{}]}, {"base_span": [813, 815], "annotations": [{}]}, {"base_span": [815, 816], "annotations": [{}]}, {"base_span": [816, 822], "annotations": [{}]}, {"base_span": [822, 823], "annotations": [{}]}, {"base_span": [824, 825], "annotations": [{}]}, {"base_span": [826, 833], "annotations": [{}]}, {"base_span": [834, 835], "annotations": [{}]}, {"base_span": [835, 837], "annotations": [{}]}, {"base_span": [837, 838], "annotations": [{}]}, {"base_span": [838, 845], "annotations": [{}]}, {"base_span": [845, 846], "annotations": [{}]}, {"base_span": [846, 848], "annotations": [{}]}, {"base_span": [848, 849], "annotations": [{}]}]}, {"name": "compound_tokens", "attributes": ["type", "normalized"], "parent": null, "enveloping": "tokens", "ambiguous": false, "serialisation_module": null, "meta": {}, "spans": [{"base_span": [[106, 107], [107, 108], [108, 109], [109, 110]], "annotations": [{"type": ["non_ending_abbreviation"], "normalized": "s.o."}]}, {"base_span": [[786, 787], [787, 788]], "annotations": [{"type": ["abbreviation"], "normalized": "a."}]}, {"base_span": [[791, 792], [792, 793], [794, 800]], "annotations": [{"type": ["name_with_initial"], "normalized": "J. Sikkut"}]}]}, {"name": "words", "attributes": ["normalized_form"], "parent": null, "enveloping": null, "ambiguous": true, "serialisation_module": null, "meta": {}, "spans": [{"base_span": [0, 5], "annotations": [{"normalized_form": null}]}, {"base_span": [6, 12], "annotations": [{"normalized_form": null}]}, {"base_span": [13, 15], "annotations": [{"normalized_form": null}]}, {"base_span": [16, 20], "annotations": [{"normalized_form": null}]}, {"base_span": [21, 25], "annotations": [{"normalized_form": null}]}, {"base_span": [26, 32], "annotations": [{"normalized_form": null}]}, {"base_span": [33, 38], "annotations": [{"normalized_form": null}]}, {"base_span": [39, 43], "annotations": [{"normalized_form": null}]}, {"base_span": [44, 49], "annotations": [{"normalized_form": null}]}, {"base_span": [50, 53], "annotations": [{"normalized_form": null}]}, {"base_span": [54, 59], "annotations": [{"normalized_form": null}]}, {"base_span": [60, 68], "annotations": [{"normalized_form": null}]}, {"base_span": [69, 77], "annotations": [{"normalized_form": null}]}, {"base_span": [77, 78], "annotations": [{"normalized_form": null}]}, {"base_span": [78, 83], "annotations": [{"normalized_form": null}]}, {"base_span": [84, 89], "annotations": [{"normalized_form": null}]}, {"base_span": [90, 93], "annotations": [{"normalized_form": null}]}, {"base_span": [94, 98], "annotations": [{"normalized_form": null}]}, {"base_span": [99, 101], "annotations": [{"normalized_form": null}]}, {"base_span": [102, 105], "annotations": [{"normalized_form": null}]}, {"base_span": [106, 110], "annotations": [{"normalized_form": "s.o."}]}, {"base_span": [111, 112], "annotations": [{"normalized_form": null}]}, {"base_span": [112, 113], "annotations": [{"normalized_form": null}]}, {"base_span": [113, 114], "annotations": [{"normalized_form": null}]}, {"base_span": [115, 118], "annotations": [{"normalized_form": null}]}, {"base_span": [119, 126], "annotations": [{"normalized_form": null}]}, {"base_span": [127, 135], "annotations": [{"normalized_form": null}]}, {"base_span": [136, 140], "annotations": [{"normalized_form": null}]}, {"base_span": [141, 149], "annotations": [{"normalized_form": null}]}, {"base_span": [150, 161], "annotations": [{"normalized_form": null}]}, {"base_span": [162, 169], "annotations": [{"normalized_form": null}]}, {"base_span": [169, 170], "annotations": [{"normalized_form": null}]}, {"base_span": [171, 174], "annotations": [{"normalized_form": null}]}, {"base_span": [175, 178], "annotations": [{"normalized_form": null}]}, {"base_span": [179, 187], "annotations": [{"normalized_form": null}]}, {"base_span": [188, 190], "annotations": [{"normalized_form": null}]}, {"base_span": [191, 195], "annotations": [{"normalized_form": null}]}, {"base_span": [196, 197], "annotations": [{"normalized_form": null}]}, {"base_span": [197, 202], "annotations": [{"normalized_form": null}]}, {"base_span": [202, 203], "annotations": [{"normalized_form": null}]}, {"base_span": [204, 208], "annotations": [{"normalized_form": null}]}, {"base_span": [209, 213], "annotations": [{"normalized_form": null}]}, {"base_span": [214, 218], "annotations": [{"normalized_form": null}]}, {"base_span": [219, 227], "annotations": [{"normalized_form": null}]}, {"base_span": [228, 230], "annotations": [{"normalized_form": null}]}, {"base_span": [231, 236], "annotations": [{"normalized_form": null}]}, {"base_span": [237, 247], "annotations": [{"normalized_form": null}]}, {"base_span": [248, 252], "annotations": [{"normalized_form": null}]}, {"base_span": [253, 257], "annotations": [{"normalized_form": null}]}, {"base_span": [258, 263], "annotations": [{"normalized_form": null}]}, {"base_span": [264, 268], "annotations": [{"normalized_form": null}]}, {"base_span": [269, 273], "annotations": [{"normalized_form": null}]}, {"base_span": [274, 277], "annotations": [{"normalized_form": null}]}, {"base_span": [278, 283], "annotations": [{"normalized_form": null}]}, {"base_span": [284, 290], "annotations": [{"normalized_form": null}]}, {"base_span": [291, 293], "annotations": [{"normalized_form": null}]}, {"base_span": [294, 299], "annotations": [{"normalized_form": null}]}, {"base_span": [300, 305], "annotations": [{"normalized_form": null}]}, {"base_span": [306, 312], "annotations": [{"normalized_form": null}]}, {"base_span": [313, 317], "annotations": [{"normalized_form": null}]}, {"base_span": [318, 325], "annotations": [{"normalized_form": null}]}, {"base_span": [326, 333], "annotations": [{"normalized_form": null}]}, {"base_span": [334, 337], "annotations": [{"normalized_form": null}]}, {"base_span": [338, 341], "annotations": [{"normalized_form": null}]}, {"base_span": [341, 342], "annotations": [{"normalized_form": null}]}, {"base_span": [343, 347], "annotations": [{"normalized_form": null}]}, {"base_span": [348, 354], "annotations": [{"normalized_form": null}]}, {"base_span": [355, 360], "annotations": [{"normalized_form": null}]}, {"base_span": [361, 366], "annotations": [{"normalized_form": null}]}, {"base_span": [367, 371], "annotations": [{"normalized_form": null}]}, {"base_span": [372, 376], "annotations": [{"normalized_form": null}]}, {"base_span": [377, 383], "annotations": [{"normalized_form": null}]}, {"base_span": [384, 386], "annotations": [{"normalized_form": null}]}, {"base_span": [387, 392], "annotations": [{"normalized_form": null}]}, {"base_span": [393, 400], "annotations": [{"normalized_form": null}]}, {"base_span": [401, 407], "annotations": [{"normalized_form": null}]}, {"base_span": [408, 409], "annotations": [{"normalized_form": null}]}, {"base_span": [410, 414], "annotations": [{"normalized_form": null}]}, {"base_span": [415, 417], "annotations": [{"normalized_form": null}]}, {"base_span": [418, 419], "annotations": [{"normalized_form": null}]}, {"base_span": [420, 426], "annotations": [{"normalized_form": null}]}, {"base_span": [427, 429], "annotations": [{"normalized_form": null}]}, {"base_span": [430, 431], "annotations": [{"normalized_form": null}]}, {"base_span": [432, 437], "annotations": [{"normalized_form": null}]}, {"base_span": [438, 444], "annotations": [{"normalized_form": null}]}, {"base_span": [445, 449], "annotations": [{"normalized_form": null}]}, {"base_span": [450, 457], "annotations": [{"normalized_form": null}]}, {"base_span": [458, 461], "annotations": [{"normalized_form": null}]}, {"base_span": [462, 467], "annotations": [{"normalized_form": null}]}, {"base_span": [468, 480], "annotations": [{"normalized_form": null}]}, {"base_span": [481, 485], "annotations": [{"normalized_form": null}]}, {"base_span": [486, 497], "annotations": [{"normalized_form": null}]}, {"base_span": [497, 498], "annotations": [{"normalized_form": null}]}, {"base_span": [498, 503], "annotations": [{"normalized_form": null}]}, {"base_span": [504, 509], "annotations": [{"normalized_form": null}]}, {"base_span": [510, 514], "annotations": [{"normalized_form": null}]}, {"base_span": [515, 520], "annotations": [{"normalized_form": null}]}, {"base_span": [521, 527], "annotations": [{"normalized_form": null}]}, {"base_span": [528, 532], "annotations": [{"normalized_form": null}]}, {"base_span": [533, 536], "annotations": [{"normalized_form": null}]}, {"base_span": [537, 541], "annotations": [{"normalized_form": null}]}, {"base_span": [542, 547], "annotations": [{"normalized_form": null}]}, {"base_span": [548, 556], "annotations": [{"normalized_form": null}]}, {"base_span": [557, 563], "annotations": [{"normalized_form": null}]}, {"base_span": [564, 570], "annotations": [{"normalized_form": null}]}, {"base_span": [571, 573], "annotations": [{"normalized_form": null}]}, {"base_span": [574, 578], "annotations": [{"normalized_form": null}]}, {"base_span": [579, 584], "annotations": [{"normalized_form": null}]}, {"base_span": [585, 590], "annotations": [{"normalized_form": null}]}, {"base_span": [591, 595], "annotations": [{"normalized_form": null}]}, {"base_span": [596, 601], "annotations": [{"normalized_form": null}]}, {"base_span": [601, 602], "annotations": [{"normalized_form": null}]}, {"base_span": [603, 608], "annotations": [{"normalized_form": null}]}, {"base_span": [609, 613], "annotations": [{"normalized_form": null}]}, {"base_span": [614, 619], "annotations": [{"normalized_form": null}]}, {"base_span": [620, 625], "annotations": [{"normalized_form": null}]}, {"base_span": [626, 631], "annotations": [{"normalized_form": null}]}, {"base_span": [632, 641], "annotations": [{"normalized_form": null}]}, {"base_span": [642, 644], "annotations": [{"normalized_form": null}]}, {"base_span": [645, 654], "annotations": [{"normalized_form": null}]}, {"base_span": [655, 662], "annotations": [{"normalized_form": null}]}, {"base_span": [663, 665], "annotations": [{"normalized_form": null}]}, {"base_span": [666, 672], "annotations": [{"normalized_form": null}]}, {"base_span": [672, 673], "annotations": [{"normalized_form": null}]}, {"base_span": [673, 678], "annotations": [{"normalized_form": null}]}, {"base_span": [679, 685], "annotations": [{"normalized_form": null}]}, {"base_span": [686, 687], "annotations": [{"normalized_form": null}]}, {"base_span": [687, 689], "annotations": [{"normalized_form": null}]}, {"base_span": [689, 690], "annotations": [{"normalized_form": null}]}, {"base_span": [690, 697], "annotations": [{"normalized_form": null}]}, {"base_span": [697, 698], "annotations": [{"normalized_form": null}]}, {"base_span": [698, 700], "annotations": [{"normalized_form": null}]}, {"base_span": [700, 701], "annotations": [{"normalized_form": null}]}, {"base_span": [701, 706], "annotations": [{"normalized_form": null}]}, {"base_span": [707, 713], "annotations": [{"normalized_form": null}]}, {"base_span": [714, 715], "annotations": [{"normalized_form": null}]}, {"base_span": [715, 717], "annotations": [{"normalized_form": null}]}, {"base_span": [717, 718], "annotations": [{"normalized_form": null}]}, {"base_span": [718, 725], "annotations": [{"normalized_form": null}]}, {"base_span": [725, 726], "annotations": [{"normalized_form": null}]}, {"base_span": [726, 728], "annotations": [{"normalized_form": null}]}, {"base_span": [728, 729], "annotations": [{"normalized_form": null}]}, {"base_span": [729, 731], "annotations": [{"normalized_form": null}]}, {"base_span": [732, 737], "annotations": [{"normalized_form": null}]}, {"base_span": [738, 752], "annotations": [{"normalized_form": null}]}, {"base_span": [753, 758], "annotations": [{"normalized_form": null}]}, {"base_span": [759, 765], "annotations": [{"normalized_form": null}]}, {"base_span": [765, 766], "annotations": [{"normalized_form": null}]}, {"base_span": [767, 785], "annotations": [{"normalized_form": null}]}, {"base_span": [786, 788], "annotations": [{"normalized_form": "a."}]}, {"base_span": [788, 789], "annotations": [{"normalized_form": null}]}, {"base_span": [789, 790], "annotations": [{"normalized_form": null}]}, {"base_span": [791, 800], "annotations": [{"normalized_form": "J. Sikkut"}]}, {"base_span": [801, 802], "annotations": [{"normalized_form": null}]}, {"base_span": [802, 804], "annotations": [{"normalized_form": null}]}, {"base_span": [804, 805], "annotations": [{"normalized_form": null}]}, {"base_span": [805, 812], "annotations": [{"normalized_form": null}]}, {"base_span": [812, 813], "annotations": [{"normalized_form": null}]}, {"base_span": [813, 815], "annotations": [{"normalized_form": null}]}, {"base_span": [815, 816], "annotations": [{"normalized_form": null}]}, {"base_span": [816, 822], "annotations": [{"normalized_form": null}]}, {"base_span": [822, 823], "annotations": [{"normalized_form": null}]}, {"base_span": [824, 825], "annotations": [{"normalized_form": null}]}, {"base_span": [826, 833], "annotations": [{"normalized_form": null}]}, {"base_span": [834, 835], "annotations": [{"normalized_form": null}]}, {"base_span": [835, 837], "annotations": [{"normalized_form": null}]}, {"base_span": [837, 838], "annotations": [{"normalized_form": null}]}, {"base_span": [838, 845], "annotations": [{"normalized_form": null}]}, {"base_span": [845, 846], "annotations": [{"normalized_form": null}]}, {"base_span": [846, 848], "annotations": [{"normalized_form": null}]}, {"base_span": [848, 849], "annotations": [{"normalized_form": null}]}]}, {"name": "morph_analysis", "attributes": ["normalized_text", "lemma", "root", "root_tokens", "ending", "clitic", "form", "partofspeech"], "parent": "words", "enveloping": null, "ambiguous": true, "serialisation_module": null, "meta": {}, "spans": [{"base_span": [0, 5], "annotations": [{"normalized_text": "Kusta", "lemma": "Kusta", "root": "Kusta", "root_tokens": ["Kusta"], "ending": "0", "clitic": "", "form": "sg n", "partofspeech": "H"}]}, {"base_span": [6, 12], "annotations": [{"normalized_text": "Paabor", "lemma": "Paabor", "root": "Paabor", "root_tokens": ["Paabor"], "ending": "0", "clitic": "", "form": "sg n", "partofspeech": "H"}]}, {"base_span": [13, 15], "annotations": [{"normalized_text": "ja", "lemma": "ja", "root": "ja", "root_tokens": ["ja"], "ending": "0", "clitic": "", "form": "", "partofspeech": "J"}]}, {"base_span": [16, 20], "annotations": [{"normalized_text": "tema", "lemma": "tema", "root": "tema", "root_tokens": ["tema"], "ending": "0", "clitic": "", "form": "sg g", "partofspeech": "P"}]}, {"base_span": [21, 25], "annotations": [{"normalized_text": "nene", "lemma": "nene", "root": "nene", "root_tokens": ["nene"], "ending": "0", "clitic": "", "form": "sg g", "partofspeech": "S"}]}, {"base_span": [26, 32], "annotations": [{"normalized_text": "endine", "lemma": "endine", "root": "endine", "root_tokens": ["endine"], "ending": "0", "clitic": "", "form": "sg n", "partofspeech": "A"}]}, {"base_span": [33, 38], "annotations": [{"normalized_text": "Miina", "lemma": "Miina", "root": "Miina", "root_tokens": ["Miina"], "ending": "0", "clitic": "", "form": "sg g", "partofspeech": "H"}]}, {"base_span": [39, 43], "annotations": [{"normalized_text": "Kala", "lemma": "kala", "root": "kala", "root_tokens": ["kala"], "ending": "0", "clitic": "", "form": "sg n", "partofspeech": "S"}]}, {"base_span": [44, 49], "annotations": [{"normalized_text": "tegid", "lemma": "tegema", "root": "tege", "root_tokens": ["tege"], "ending": "id", "clitic": "", "form": "sid", "partofspeech": "V"}]}, {"base_span": [50, 53], "annotations": [{"normalized_text": "oma", "lemma": "oma", "root": "oma", "root_tokens": ["oma"], "ending": "0", "clitic": "", "form": "sg g", "partofspeech": "P"}]}, {"base_span": [54, 59], "annotations": [{"normalized_text": "wahel", "lemma": "wahe", "root": "wahe", "root_tokens": ["wahe"], "ending": "l", "clitic": "", "form": "sg ad", "partofspeech": "S"}]}, {"base_span": [60, 68], "annotations": [{"normalized_text": "järgmise", "lemma": "järgmine", "root": "järgmine", "root_tokens": ["järgmine"], "ending": "0", "clitic": "", "form": "sg g", "partofspeech": "A"}]}, {"base_span": [69, 77], "annotations": [{"normalized_text": "leppingu", "lemma": "lepping", "root": "lep_ping", "root_tokens": ["lep", "ping"], "ending": "0", "clitic": "", "form": "sg g", "partofspeech": "S"}]}, {"base_span": [77, 78], "annotations": [{"normalized_text": ":", "lemma": ":", "root": ":", "root_tokens": [":"], "ending": "", "clitic": "", "form": "", "partofspeech": "Z"}]}, {"base_span": [78, 83], "annotations": [{"normalized_text": "Miina", "lemma": "Miina", "root": "Miina", "root_tokens": ["Miina"], "ending": "0", "clitic": "", "form": "sg n", "partofspeech": "H"}]}, {"base_span": [84, 89], "annotations": [{"normalized_text": "annab", "lemma": "andma", "root": "and", "root_tokens": ["and"], "ending": "b", "clitic": "", "form": "b", "partofspeech": "V"}]}, {"base_span": [90, 93], "annotations": [{"normalized_text": "oma", "lemma": "oma", "root": "oma", "root_tokens": ["oma"], "ending": "0", "clitic": "", "form": "sg g", "partofspeech": "P"}]}, {"base_span": [94, 98], "annotations": [{"normalized_text": "maja", "lemma": "maja", "root": "maja", "root_tokens": ["maja"], "ending": "0", "clitic": "", "form": "sg g", "partofspeech": "S"}]}, {"base_span": [99, 101], "annotations": [{"normalized_text": "ja", "lemma": "ja", "root": "ja", "root_tokens": ["ja"], "ending": "0", "clitic": "", "form": "", "partofspeech": "J"}]}, {"base_span": [102, 105], "annotations": [{"normalized_text": "maa", "lemma": "maa", "root": "maa", "root_tokens": ["maa"], "ending": "0", "clitic": "", "form": "sg g", "partofspeech": "S"}]}, {"base_span": [106, 110], "annotations": [{"normalized_text": "s.o.", "lemma": "s.o", "root": "s.o", "root_tokens": ["s.o"], "ending": "0", "clitic": "", "form": "?", "partofspeech": "Y"}]}, {"base_span": [111, 112], "annotations": [{"normalized_text": "1", "lemma": "1", "root": "1", "root_tokens": ["1"], "ending": "0", "clitic": "", "form": "?", "partofspeech": "N"}]}, {"base_span": [112, 113], "annotations": [{"normalized_text": "/", "lemma": "/", "root": "/", "root_tokens": ["/"], "ending": "", "clitic": "", "form": "", "partofspeech": "Z"}]}, {"base_span": [113, 114], "annotations": [{"normalized_text": "4", "lemma": "4", "root": "4", "root_tokens": ["4"], "ending": "0", "clitic": "", "form": "?", "partofspeech": "N"}]}, {"base_span": [115, 118], "annotations": [{"normalized_text": "osa", "lemma": "osa", "root": "osa", "root_tokens": ["osa"], "ending": "0", "clitic": "", "form": "sg n", "partofspeech": "S"}]}, {"base_span": [119, 126], "annotations": [{"normalized_text": "kõigest", "lemma": "kõigest", "root": "kõigest", "root_tokens": ["kõigest"], "ending": "0", "clitic": "", "form": "", "partofspeech": "D"}]}, {"base_span": [127, 135], "annotations": [{"normalized_text": "Räustawa", "lemma": "Räustawa", "root": "Räustawa", "root_tokens": ["Räustawa"], "ending": "0", "clitic": "", "form": "sg g", "partofspeech": "H"}]}, {"base_span": [136, 140], "annotations": [{"normalized_text": "talu", "lemma": "talu", "root": "talu", "root_tokens": ["talu"], "ending": "0", "clitic": "", "form": "sg g", "partofspeech": "S"}]}, {"base_span": [141, 149], "annotations": [{"normalized_text": "krundist", "lemma": "krunt", "root": "krunt", "root_tokens": ["krunt"], "ending": "st", "clitic": "", "form": "sg el", "partofspeech": "S"}]}, {"base_span": [150, 161], "annotations": [{"normalized_text": "Ahjawallast", "lemma": "Ahjawalla", "root": "Ahjawalla", "root_tokens": ["Ahjawalla"], "ending": "st", "clitic": "", "form": "sg el", "partofspeech": "H"}]}, {"base_span": [162, 169], "annotations": [{"normalized_text": "Kustale", "lemma": "Kusta", "root": "Kusta", "root_tokens": ["Kusta"], "ending": "le", "clitic": "", "form": "sg all", "partofspeech": "H"}]}, {"base_span": [169, 170], "annotations": [{"normalized_text": ",", "lemma": ",", "root": ",", "root_tokens": [","], "ending": "", "clitic": "", "form": "", "partofspeech": "Z"}]}, {"base_span": [171, 174], "annotations": [{"normalized_text": "kes", "lemma": "kes", "root": "kes", "root_tokens": ["kes"], "ending": "0", "clitic": "", "form": "pl n", "partofspeech": "P"}, {"normalized_text": "kes", "lemma": "kes", "root": "kes", "root_tokens": ["kes"], "ending": "0", "clitic": "", "form": "sg n", "partofspeech": "P"}]}, {"base_span": [175, 178], "annotations": [{"normalized_text": "kui", "lemma": "kui", "root": "kui", "root_tokens": ["kui"], "ending": "0", "clitic": "", "form": "", "partofspeech": "D"}, {"normalized_text": "kui", "lemma": "kui", "root": "kui", "root_tokens": ["kui"], "ending": "0", "clitic": "", "form": "", "partofspeech": "J"}]}, {"base_span": [179, 187], "annotations": [{"normalized_text": "peremees", "lemma": "peremees", "root": "pere_mees", "root_tokens": ["pere", "mees"], "ending": "0", "clitic": "", "form": "sg n", "partofspeech": "S"}]}, {"base_span": [188, 190], "annotations": [{"normalized_text": "ja", "lemma": "ja", "root": "ja", "root_tokens": ["ja"], "ending": "0", "clitic": "", "form": "", "partofspeech": "J"}]}, {"base_span": [191, 195], "annotations": [{"normalized_text": "tema", "lemma": "tema", "root": "tema", "root_tokens": ["tema"], "ending": "0", "clitic": "", "form": "sg g", "partofspeech": "P"}]}, {"base_span": [196, 197], "annotations": [{"normalized_text": "(", "lemma": "(", "root": "(", "root_tokens": ["("], "ending": "", "clitic": "", "form": "", "partofspeech": "Z"}]}, {"base_span": [197, 202], "annotations": [{"normalized_text": "Miina", "lemma": "Miina", "root": "Miina", "root_tokens": ["Miina"], "ending": "0", "clitic": "", "form": "sg n", "partofspeech": "H"}]}, {"base_span": [202, 203], "annotations": [{"normalized_text": ")", "lemma": ")", "root": ")", "root_tokens": [")"], "ending": "", "clitic": "", "form": "", "partofspeech": "Z"}]}, {"base_span": [204, 208], "annotations": [{"normalized_text": "mees", "lemma": "mees", "root": "mees", "root_tokens": ["mees"], "ending": "0", "clitic": "", "form": "sg n", "partofspeech": "S"}]}, {"base_span": [209, 213], "annotations": [{"normalized_text": "seal", "lemma": "seal", "root": "seal", "root_tokens": ["seal"], "ending": "0", "clitic": "", "form": "", "partofspeech": "D"}]}, {"base_span": [214, 218], "annotations": [{"normalized_text": "sees", "lemma": "sees", "root": "sees", "root_tokens": ["sees"], "ending": "0", "clitic": "", "form": "", "partofspeech": "D"}]}, {"base_span": [219, 227], "annotations": [{"normalized_text": "walitseb", "lemma": "walitsema", "root": "walitse", "root_tokens": ["walitse"], "ending": "b", "clitic": "", "form": "b", "partofspeech": "V"}]}, {"base_span": [228, 230], "annotations": [{"normalized_text": "ja", "lemma": "ja", "root": "ja", "root_tokens": ["ja"], "ending": "0", "clitic": "", "form": "", "partofspeech": "J"}]}, {"base_span": [231, 236], "annotations": [{"normalized_text": "kelle", "lemma": "kes", "root": "kes", "root_tokens": ["kes"], "ending": "0", "clitic": "", "form": "pl g", "partofspeech": "P"}, {"normalized_text": "kelle", "lemma": "kes", "root": "kes", "root_tokens": ["kes"], "ending": "0", "clitic": "", "form": "sg g", "partofspeech": "P"}]}, {"base_span": [237, 247], "annotations": [{"normalized_text": "omanduseks", "lemma": "omandus", "root": "omandus", "root_tokens": ["omandus"], "ending": "ks", "clitic": "", "form": "sg tr", "partofspeech": "S"}]}, {"base_span": [248, 252], "annotations": [{"normalized_text": "tema", "lemma": "tema", "root": "tema", "root_tokens": ["tema"], "ending": "0", "clitic": "", "form": "sg n", "partofspeech": "P"}]}, {"base_span": [253, 257], "annotations": [{"normalized_text": "jääb", "lemma": "jääma", "root": "jää", "root_tokens": ["jää"], "ending": "b", "clitic": "", "form": "b", "partofspeech": "V"}]}, {"base_span": [258, 263], "annotations": [{"normalized_text": "selle", "lemma": "see", "root": "see", "root_tokens": ["see"], "ending": "0", "clitic": "", "form": "sg g", "partofspeech": "P"}]}, {"base_span": [264, 268], "annotations": [{"normalized_text": "eest", "lemma": "eest", "root": "eest", "root_tokens": ["eest"], "ending": "0", "clitic": "", "form": "", "partofspeech": "K"}]}, {"base_span": [269, 273], "annotations": [{"normalized_text": "peab", "lemma": "pidama", "root": "pida", "root_tokens": ["pida"], "ending": "b", "clitic": "", "form": "b", "partofspeech": "V"}]}, {"base_span": [274, 277], "annotations": [{"normalized_text": "aga", "lemma": "aga", "root": "aga", "root_tokens": ["aga"], "ending": "0", "clitic": "", "form": "", "partofspeech": "J"}]}, {"base_span": [278, 283], "annotations": [{"normalized_text": "Kusta", "lemma": "Kusta", "root": "Kusta", "root_tokens": ["Kusta"], "ending": "0", "clitic": "", "form": "sg n", "partofspeech": "H"}]}, {"base_span": [284, 290], "annotations": [{"normalized_text": "Paabor", "lemma": "Paabor", "root": "Paabor", "root_tokens": ["Paabor"], "ending": "0", "clitic": "", "form": "sg n", "partofspeech": "H"}]}, {"base_span": [291, 293], "annotations": [{"normalized_text": "ja", "lemma": "ja", "root": "ja", "root_tokens": ["ja"], "ending": "0", "clitic": "", "form": "", "partofspeech": "J"}]}, {"base_span": [294, 299], "annotations": [{"normalized_text": "lubab", "lemma": "lubama", "root": "luba", "root_tokens": ["luba"], "ending": "b", "clitic": "", "form": "b", "partofspeech": "V"}]}, {"base_span": [300, 305], "annotations": [{"normalized_text": "Miina", "lemma": "Miina", "root": "Miina", "root_tokens": ["Miina"], "ending": "0", "clitic": "", "form": "sg g", "partofspeech": "H"}]}, {"base_span": [306, 312], "annotations": [{"normalized_text": "esimse", "lemma": "esimse", "root": "esimse", "root_tokens": ["esimse"], "ending": "0", "clitic": "", "form": "sg g", "partofspeech": "S"}]}, {"base_span": [313, 317], "annotations": [{"normalized_text": "mehe", "lemma": "mees", "root": "mees", "root_tokens": ["mees"], "ending": "0", "clitic": "", "form": "sg g", "partofspeech": "S"}]}, {"base_span": [318, 325], "annotations": [{"normalized_text": "lapsele", "lemma": "laps", "root": "laps", "root_tokens": ["laps"], "ending": "le", "clitic": "", "form": "sg all", "partofspeech": "S"}]}, {"base_span": [326, 333], "annotations": [{"normalized_text": "Jaanile", "lemma": "Jaan", "root": "Jaan", "root_tokens": ["Jaan"], "ending": "le", "clitic": "", "form": "sg all", "partofspeech": "H"}, {"normalized_text": "Jaanile", "lemma": "Jaani", "root": "Jaani", "root_tokens": ["Jaani"], "ending": "le", "clitic": "", "form": "sg all", "partofspeech": "H"}]}, {"base_span": [334, 337], "annotations": [{"normalized_text": "100", "lemma": "100", "root": "100", "root_tokens": ["100"], "ending": "0", "clitic": "", "form": "?", "partofspeech": "N"}]}, {"base_span": [338, 341], "annotations": [{"normalized_text": "rbl", "lemma": "rbl", "root": "rbl", "root_tokens": ["rbl"], "ending": "0", "clitic": "", "form": "?", "partofspeech": "Y"}]}, {"base_span": [341, 342], "annotations": [{"normalized_text": ".", "lemma": ".", "root": ".", "root_tokens": ["."], "ending": "", "clitic": "", "form": "", "partofspeech": "Z"}]}, {"base_span": [343, 347], "annotations": [{"normalized_text": "1895", "lemma": "1895", "root": "1895", "root_tokens": ["1895"], "ending": "0", "clitic": "", "form": "?", "partofspeech": "N"}]}, {"base_span": [348, 354], "annotations": [{"normalized_text": "aastal", "lemma": "aasta", "root": "aasta", "root_tokens": ["aasta"], "ending": "l", "clitic": "", "form": "sg ad", "partofspeech": "S"}]}, {"base_span": [355, 360], "annotations": [{"normalized_text": "kohtu", "lemma": "kohus", "root": "kohus", "root_tokens": ["kohus"], "ending": "0", "clitic": "", "form": "sg g", "partofspeech": "S"}]}, {"base_span": [361, 366], "annotations": [{"normalized_text": "kätte", "lemma": "kätte", "root": "kätte", "root_tokens": ["kätte"], "ending": "0", "clitic": "", "form": "", "partofspeech": "K"}]}, {"base_span": [367, 371], "annotations": [{"normalized_text": "hoiu", "lemma": "hoid", "root": "hoid", "root_tokens": ["hoid"], "ending": "0", "clitic": "", "form": "sg g", "partofspeech": "S"}]}, {"base_span": [372, 376], "annotations": [{"normalized_text": "alla", "lemma": "alla", "root": "alla", "root_tokens": ["alla"], "ending": "0", "clitic": "", "form": "", "partofspeech": "K"}]}, {"base_span": [377, 383], "annotations": [{"normalized_text": "maksma", "lemma": "maksma", "root": "maks", "root_tokens": ["maks"], "ending": "ma", "clitic": "", "form": "ma", "partofspeech": "V"}]}, {"base_span": [384, 386], "annotations": [{"normalized_text": "ja", "lemma": "ja", "root": "ja", "root_tokens": ["ja"], "ending": "0", "clitic": "", "form": "", "partofspeech": "J"}]}, {"base_span": [387, 392], "annotations": [{"normalized_text": "tütar", "lemma": "tütar", "root": "tütar", "root_tokens": ["tütar"], "ending": "0", "clitic": "", "form": "sg n", "partofspeech": "S"}]}, {"base_span": [393, 400], "annotations": [{"normalized_text": "Juulale", "lemma": "Juulale", "root": "Juulale", "root_tokens": ["Juulale"], "ending": "0", "clitic": "", "form": "sg n", "partofspeech": "H"}]}, {"base_span": [401, 407], "annotations": [{"normalized_text": "Semmel", "lemma": "Semmel", "root": "Semmel", "root_tokens": ["Semmel"], "ending": "0", "clitic": "", "form": "sg n", "partofspeech": "H"}]}, {"base_span": [408, 409], "annotations": [{"normalized_text": "1", "lemma": "1", "root": "1", "root_tokens": ["1"], "ending": "0", "clitic": "", "form": "?", "partofspeech": "N"}]}, {"base_span": [410, 414], "annotations": [{"normalized_text": "lehm", "lemma": "lehm", "root": "lehm", "root_tokens": ["lehm"], "ending": "0", "clitic": "", "form": "sg n", "partofspeech": "S"}]}, {"base_span": [415, 417], "annotations": [{"normalized_text": "ja", "lemma": "ja", "root": "ja", "root_tokens": ["ja"], "ending": "0", "clitic": "", "form": "", "partofspeech": "J"}]}, {"base_span": [418, 419], "annotations": [{"normalized_text": "1", "lemma": "1", "root": "1", "root_tokens": ["1"], "ending": "0", "clitic": "", "form": "?", "partofspeech": "N"}]}, {"base_span": [420, 426], "annotations": [{"normalized_text": "lammas", "lemma": "lammas", "root": "lammas", "root_tokens": ["lammas"], "ending": "0", "clitic": "", "form": "sg n", "partofspeech": "S"}]}, {"base_span": [427, 429], "annotations": [{"normalized_text": "ja", "lemma": "ja", "root": "ja", "root_tokens": ["ja"], "ending": "0", "clitic": "", "form": "", "partofspeech": "J"}]}, {"base_span": [430, 431], "annotations": [{"normalized_text": "1", "lemma": "1", "root": "1", "root_tokens": ["1"], "ending": "0", "clitic": "", "form": "?", "partofspeech": "N"}]}, {"base_span": [432, 437], "annotations": [{"normalized_text": "rõiwa", "lemma": "rõiwa", "root": "rõiwa", "root_tokens": ["rõiwa"], "ending": "0", "clitic": "", "form": "sg g", "partofspeech": "S"}]}, {"base_span": [438, 444], "annotations": [{"normalized_text": "luhwri", "lemma": "luhwr", "root": "luhwr", "root_tokens": ["luhwr"], "ending": "0", "clitic": "", "form": "adt", "partofspeech": "S"}]}, {"base_span": [445, 449], "annotations": [{"normalized_text": "ilma", "lemma": "ilma", "root": "ilma", "root_tokens": ["ilma"], "ending": "0", "clitic": "", "form": "", "partofspeech": "K"}]}, {"base_span": [450, 457], "annotations": [{"normalized_text": "rõiwata", "lemma": "rõiwata", "root": "rõiwata", "root_tokens": ["rõiwata"], "ending": "0", "clitic": "", "form": "sg g", "partofspeech": "S"}]}, {"base_span": [458, 461], "annotations": [{"normalized_text": "kui", "lemma": "kui", "root": "kui", "root_tokens": ["kui"], "ending": "0", "clitic": "", "form": "", "partofspeech": "D"}, {"normalized_text": "kui", "lemma": "kui", "root": "kui", "root_tokens": ["kui"], "ending": "0", "clitic": "", "form": "", "partofspeech": "J"}]}, {"base_span": [462, 467], "annotations": [{"normalized_text": "sõsar", "lemma": "sõsar", "root": "sõsar", "root_tokens": ["sõsar"], "ending": "0", "clitic": "", "form": "sg n", "partofspeech": "S"}]}, {"base_span": [468, 480], "annotations": [{"normalized_text": "täisealiseks", "lemma": "täisealine", "root": "täis_ealine", "root_tokens": ["täis", "ealine"], "ending": "ks", "clitic": "", "form": "sg tr", "partofspeech": "A"}]}, {"base_span": [481, 485], "annotations": [{"normalized_text": "saab", "lemma": "saama", "root": "saa", "root_tokens": ["saa"], "ending": "b", "clitic": "", "form": "b", "partofspeech": "V"}]}, {"base_span": [486, 497], "annotations": [{"normalized_text": "wäljamaksma", "lemma": "wäljamaksma", "root": "wäljamaksma", "root_tokens": ["wäljamaksma"], "ending": "0", "clitic": "", "form": "sg n", "partofspeech": "S"}]}, {"base_span": [497, 498], "annotations": [{"normalized_text": ".", "lemma": ".", "root": ".", "root_tokens": ["."], "ending": "", "clitic": "", "form": "", "partofspeech": "Z"}]}, {"base_span": [498, 503], "annotations": [{"normalized_text": "Peale", "lemma": "peale", "root": "peale", "root_tokens": ["peale"], "ending": "0", "clitic": "", "form": "", "partofspeech": "K"}]}, {"base_span": [504, 509], "annotations": [{"normalized_text": "selle", "lemma": "see", "root": "see", "root_tokens": ["see"], "ending": "0", "clitic": "", "form": "sg g", "partofspeech": "P"}]}, {"base_span": [510, 514], "annotations": [{"normalized_text": "peab", "lemma": "pidama", "root": "pida", "root_tokens": ["pida"], "ending": "b", "clitic": "", "form": "b", "partofspeech": "V"}]}, {"base_span": [515, 520], "annotations": [{"normalized_text": "Kusta", "lemma": "Kusta", "root": "Kusta", "root_tokens": ["Kusta"], "ending": "0", "clitic": "", "form": "sg g", "partofspeech": "H"}]}, {"base_span": [521, 527], "annotations": [{"normalized_text": "paabor", "lemma": "paabor", "root": "paabor", "root_tokens": ["paabor"], "ending": "0", "clitic": "", "form": "sg n", "partofspeech": "S"}]}, {"base_span": [528, 532], "annotations": [{"normalized_text": "weel", "lemma": "wee", "root": "wee", "root_tokens": ["wee"], "ending": "l", "clitic": "", "form": "sg ad", "partofspeech": "S"}]}, {"base_span": [533, 536], "annotations": [{"normalized_text": "oma", "lemma": "oma", "root": "oma", "root_tokens": ["oma"], "ending": "0", "clitic": "", "form": "sg g", "partofspeech": "P"}]}, {"base_span": [537, 541], "annotations": [{"normalized_text": "ämma", "lemma": "ämm", "root": "ämm", "root_tokens": ["ämm"], "ending": "0", "clitic": "", "form": "sg g", "partofspeech": "S"}]}, {"base_span": [542, 547], "annotations": [{"normalized_text": "Marit", "lemma": "Mari", "root": "Mari", "root_tokens": ["Mari"], "ending": "t", "clitic": "", "form": "sg p", "partofspeech": "H"}]}, {"base_span": [548, 556], "annotations": [{"normalized_text": "auusaste", "lemma": "auusane", "root": "auusane", "root_tokens": ["auusane"], "ending": "te", "clitic": "", "form": "pl g", "partofspeech": "A"}]}, {"base_span": [557, 563], "annotations": [{"normalized_text": "ülewal", "lemma": "ülewa", "root": "ülewa", "root_tokens": ["ülewa"], "ending": "l", "clitic": "", "form": "sg ad", "partofspeech": "S"}]}, {"base_span": [564, 570], "annotations": [{"normalized_text": "pidama", "lemma": "pidama", "root": "pida", "root_tokens": ["pida"], "ending": "ma", "clitic": "", "form": "ma", "partofspeech": "V"}]}, {"base_span": [571, 573], "annotations": [{"normalized_text": "ja", "lemma": "ja", "root": "ja", "root_tokens": ["ja"], "ending": "0", "clitic": "", "form": "", "partofspeech": "J"}]}, {"base_span": [574, 578], "annotations": [{"normalized_text": "teda", "lemma": "tema", "root": "tema", "root_tokens": ["tema"], "ending": "da", "clitic": "", "form": "sg p", "partofspeech": "P"}]}, {"base_span": [579, 584], "annotations": [{"normalized_text": "matma", "lemma": "matma", "root": "mat", "root_tokens": ["mat"], "ending": "ma", "clitic": "", "form": "ma", "partofspeech": "V"}]}, {"base_span": [585, 590], "annotations": [{"normalized_text": "peale", "lemma": "peale", "root": "peale", "root_tokens": ["peale"], "ending": "0", "clitic": "", "form": "", "partofspeech": "D"}]}, {"base_span": [591, 595], "annotations": [{"normalized_text": "tema", "lemma": "tema", "root": "tema", "root_tokens": ["tema"], "ending": "0", "clitic": "", "form": "sg g", "partofspeech": "P"}]}, {"base_span": [596, 601], "annotations": [{"normalized_text": "surma", "lemma": "surm", "root": "surm", "root_tokens": ["surm"], "ending": "0", "clitic": "", "form": "sg p", "partofspeech": "S"}]}, {"base_span": [601, 602], "annotations": [{"normalized_text": ".", "lemma": ".", "root": ".", "root_tokens": ["."], "ending": "", "clitic": "", "form": "", "partofspeech": "Z"}]}, {"base_span": [603, 608], "annotations": [{"normalized_text": "Kusta", "lemma": "Kusta", "root": "Kusta", "root_tokens": ["Kusta"], "ending": "0", "clitic": "", "form": "sg n", "partofspeech": "H"}]}, {"base_span": [609, 613], "annotations": [{"normalized_text": "peab", "lemma": "pidama", "root": "pida", "root_tokens": ["pida"], "ending": "b", "clitic": "", "form": "b", "partofspeech": "V"}]}, {"base_span": [614, 619], "annotations": [{"normalized_text": "Miina", "lemma": "Miina", "root": "Miina", "root_tokens": ["Miina"], "ending": "0", "clitic": "", "form": "sg g", "partofspeech": "H"}]}, {"base_span": [620, 625], "annotations": [{"normalized_text": "poega", "lemma": "poeg", "root": "poeg", "root_tokens": ["poeg"], "ending": "0", "clitic": "", "form": "sg p", "partofspeech": "S"}]}, {"base_span": [626, 631], "annotations": [{"normalized_text": "Jaani", "lemma": "Jaan", "root": "Jaan", "root_tokens": ["Jaan"], "ending": "0", "clitic": "", "form": "sg g", "partofspeech": "H"}, {"normalized_text": "Jaani", "lemma": "Jaani", "root": "Jaani", "root_tokens": ["Jaani"], "ending": "0", "clitic": "", "form": "sg g", "partofspeech": "H"}]}, {"base_span": [632, 641], "annotations": [{"normalized_text": "koolitama", "lemma": "koolitama", "root": "koolita", "root_tokens": ["koolita"], "ending": "ma", "clitic": "", "form": "ma", "partofspeech": "V"}]}, {"base_span": [642, 644], "annotations": [{"normalized_text": "ja", "lemma": "ja", "root": "ja", "root_tokens": ["ja"], "ending": "0", "clitic": "", "form": "", "partofspeech": "J"}]}, {"base_span": [645, 654], "annotations": [{"normalized_text": "kaswatama", "lemma": "kaswatama", "root": "kaswata", "root_tokens": ["kaswata"], "ending": "ma", "clitic": "", "form": "ma", "partofspeech": "V"}]}, {"base_span": [655, 662], "annotations": [{"normalized_text": "niisama", "lemma": "niisama", "root": "nii_sama", "root_tokens": ["nii", "sama"], "ending": "0", "clitic": "", "form": "", "partofspeech": "D"}]}, {"base_span": [663, 665], "annotations": [{"normalized_text": "ka", "lemma": "ka", "root": "ka", "root_tokens": ["ka"], "ending": "0", "clitic": "", "form": "", "partofspeech": "D"}]}, {"base_span": [666, 672], "annotations": [{"normalized_text": "Juulat", "lemma": "Juulat", "root": "Juulat", "root_tokens": ["Juulat"], "ending": "0", "clitic": "", "form": "sg n", "partofspeech": "H"}]}, {"base_span": [672, 673], "annotations": [{"normalized_text": ".", "lemma": ".", "root": ".", "root_tokens": ["."], "ending": "", "clitic": "", "form": "", "partofspeech": "Z"}]}, {"base_span": [673, 678], "annotations": [{"normalized_text": "Kusta", "lemma": "Kusta", "root": "Kusta", "root_tokens": ["Kusta"], "ending": "0", "clitic": "", "form": "sg n", "partofspeech": "H"}]}, {"base_span": [679, 685], "annotations": [{"normalized_text": "Paabor", "lemma": "Paabor", "root": "Paabor", "root_tokens": ["Paabor"], "ending": "0", "clitic": "", "form": "sg n", "partofspeech": "H"}]}, {"base_span": [686, 687], "annotations": [{"normalized_text": "&", "lemma": "&", "root": "&", "root_tokens": ["&"], "ending": "0", "clitic": "", "form": "", "partofspeech": "J"}]}, {"base_span": [687, 689], "annotations": [{"normalized_text": "lt", "lemma": "lt", "root": "lt", "root_tokens": ["lt"], "ending": "0", "clitic": "", "form": "?", "partofspeech": "Y"}]}, {"base_span": [689, 690], "annotations": [{"normalized_text": ";", "lemma": ";", "root": ";", "root_tokens": [";"], "ending": "", "clitic": "", "form": "", "partofspeech": "Z"}]}, {"base_span": [690, 697], "annotations": [{"normalized_text": "allkiri", "lemma": "allkiri", "root": "all_kiri", "root_tokens": ["all", "kiri"], "ending": "0", "clitic": "", "form": "sg n", "partofspeech": "S"}]}, {"base_span": [697, 698], "annotations": [{"normalized_text": "&", "lemma": "&", "root": "&", "root_tokens": ["&"], "ending": "0", "clitic": "", "form": "", "partofspeech": "J"}]}, {"base_span": [698, 700], "annotations": [{"normalized_text": "gt", "lemma": "gt", "root": "gt", "root_tokens": ["gt"], "ending": "0", "clitic": "", "form": "?", "partofspeech": "Y"}]}, {"base_span": [700, 701], "annotations": [{"normalized_text": ";", "lemma": ";", "root": ";", "root_tokens": [";"], "ending": "", "clitic": "", "form": "", "partofspeech": "Z"}]}, {"base_span": [701, 706], "annotations": [{"normalized_text": "Miina", "lemma": "Miina", "root": "Miina", "root_tokens": ["Miina"], "ending": "0", "clitic": "", "form": "sg n", "partofspeech": "H"}]}, {"base_span": [707, 713], "annotations": [{"normalized_text": "Paabor", "lemma": "Paabor", "root": "Paabor", "root_tokens": ["Paabor"], "ending": "0", "clitic": "", "form": "sg n", "partofspeech": "H"}]}, {"base_span": [714, 715], "annotations": [{"normalized_text": "&", "lemma": "&", "root": "&", "root_tokens": ["&"], "ending": "0", "clitic": "", "form": "", "partofspeech": "J"}]}, {"base_span": [715, 717], "annotations": [{"normalized_text": "lt", "lemma": "lt", "root": "lt", "root_tokens": ["lt"], "ending": "0", "clitic": "", "form": "?", "partofspeech": "Y"}]}, {"base_span": [717, 718], "annotations": [{"normalized_text": ";", "lemma": ";", "root": ";", "root_tokens": [";"], "ending": "", "clitic": "", "form": "", "partofspeech": "Z"}]}, {"base_span": [718, 725], "annotations": [{"normalized_text": "allkiri", "lemma": "allkiri", "root": "all_kiri", "root_tokens": ["all", "kiri"], "ending": "0", "clitic": "", "form": "sg n", "partofspeech": "S"}]}, {"base_span": [725, 726], "annotations": [{"normalized_text": "&", "lemma": "&", "root": "&", "root_tokens": ["&"], "ending": "0", "clitic": "", "form": "", "partofspeech": "J"}]}, {"base_span": [726, 728], "annotations": [{"normalized_text": "gt", "lemma": "gt", "root": "gt", "root_tokens": ["gt"], "ending": "0", "clitic": "", "form": "?", "partofspeech": "Y"}]}, {"base_span": [728, 729], "annotations": [{"normalized_text": ";", "lemma": ";", "root": ";", "root_tokens": [";"], "ending": "", "clitic": "", "form": "", "partofspeech": "Z"}]}, {"base_span": [729, 731], "annotations": [{"normalized_text": "Et", "lemma": "et", "root": "et", "root_tokens": ["et"], "ending": "0", "clitic": "", "form": "", "partofspeech": "J"}]}, {"base_span": [732, 737], "annotations": [{"normalized_text": "Kohus", "lemma": "kohus", "root": "kohus", "root_tokens": ["kohus"], "ending": "0", "clitic": "", "form": "sg n", "partofspeech": "S"}]}, {"base_span": [738, 752], "annotations": [{"normalized_text": "kokkuleppijaid", "lemma": "kokkuleppija", "root": "kokku_leppi=ja", "root_tokens": ["kokku", "leppija"], "ending": "id", "clitic": "", "form": "pl p", "partofspeech": "S"}]}, {"base_span": [753, 758], "annotations": [{"normalized_text": "pooli", "lemma": "pool", "root": "pool", "root_tokens": ["pool"], "ending": "i", "clitic": "", "form": "pl p", "partofspeech": "N"}]}, {"base_span": [759, 765], "annotations": [{"normalized_text": "tunneb", "lemma": "tundma", "root": "tund", "root_tokens": ["tund"], "ending": "b", "clitic": "", "form": "b", "partofspeech": "V"}]}, {"base_span": [765, 766], "annotations": [{"normalized_text": ",", "lemma": ",", "root": ",", "root_tokens": [","], "ending": "", "clitic": "", "form": "", "partofspeech": "Z"}]}, {"base_span": [767, 785], "annotations": [{"normalized_text": "tunnistabEesistuja", "lemma": "tunnistabeesistuja", "root": "tunnistab_ees_istuja", "root_tokens": ["tunnistab", "ees", "istuja"], "ending": "0", "clitic": "", "form": "sg n", "partofspeech": "S"}]}, {"base_span": [786, 788], "annotations": [{"normalized_text": "a.", "lemma": "a", "root": "a", "root_tokens": ["a"], "ending": "0", "clitic": "", "form": "?", "partofspeech": "Y"}]}, {"base_span": [788, 789], "annotations": [{"normalized_text": "s", "lemma": "s", "root": "s", "root_tokens": ["s"], "ending": "0", "clitic": "", "form": "?", "partofspeech": "Y"}]}, {"base_span": [789, 790], "annotations": [{"normalized_text": ".", "lemma": ".", "root": ".", "root_tokens": ["."], "ending": "", "clitic": "", "form": "", "partofspeech": "Z"}]}, {"base_span": [791, 800], "annotations": [{"normalized_text": "J. Sikkut", "lemma": "J. Sikkut", "root": "J. _Sikkut", "root_tokens": ["J. ", "Sikkut"], "ending": "0", "clitic": "", "form": "?", "partofspeech": "H"}]}, {"base_span": [801, 802], "annotations": [{"normalized_text": "&", "lemma": "&", "root": "&", "root_tokens": ["&"], "ending": "0", "clitic": "", "form": "", "partofspeech": "J"}]}, {"base_span": [802, 804], "annotations": [{"normalized_text": "lt", "lemma": "lt", "root": "lt", "root_tokens": ["lt"], "ending": "0", "clitic": "", "form": "?", "partofspeech": "Y"}]}, {"base_span": [804, 805], "annotations": [{"normalized_text": ";", "lemma": ";", "root": ";", "root_tokens": [";"], "ending": "", "clitic": "", "form": "", "partofspeech": "Z"}]}, {"base_span": [805, 812], "annotations": [{"normalized_text": "allkiri", "lemma": "allkiri", "root": "all_kiri", "root_tokens": ["all", "kiri"], "ending": "0", "clitic": "", "form": "sg n", "partofspeech": "S"}]}, {"base_span": [812, 813], "annotations": [{"normalized_text": "&", "lemma": "&", "root": "&", "root_tokens": ["&"], "ending": "0", "clitic": "", "form": "", "partofspeech": "J"}]}, {"base_span": [813, 815], "annotations": [{"normalized_text": "gt", "lemma": "gt", "root": "gt", "root_tokens": ["gt"], "ending": "0", "clitic": "", "form": "?", "partofspeech": "Y"}]}, {"base_span": [815, 816], "annotations": [{"normalized_text": ";", "lemma": ";", "root": ";", "root_tokens": [";"], "ending": "", "clitic": "", "form": "", "partofspeech": "Z"}]}, {"base_span": [816, 822], "annotations": [{"normalized_text": "Kirjut", "lemma": "Kirjut", "root": "Kirjut", "root_tokens": ["Kirjut"], "ending": "0", "clitic": "", "form": "sg n", "partofspeech": "H"}]}, {"base_span": [822, 823], "annotations": [{"normalized_text": ":", "lemma": ":", "root": ":", "root_tokens": [":"], "ending": "", "clitic": "", "form": "", "partofspeech": "Z"}]}, {"base_span": [824, 825], "annotations": [{"normalized_text": "J", "lemma": "J", "root": "J", "root_tokens": ["J"], "ending": "0", "clitic": "", "form": "?", "partofspeech": "Y"}]}, {"base_span": [826, 833], "annotations": [{"normalized_text": "Puusepp", "lemma": "Puusepp", "root": "Puu_sepp", "root_tokens": ["Puu", "sepp"], "ending": "0", "clitic": "", "form": "sg n", "partofspeech": "H"}, {"normalized_text": "Puusepp", "lemma": "Puusepp", "root": "Puusepp", "root_tokens": ["Puusepp"], "ending": "0", "clitic": "", "form": "sg n", "partofspeech": "H"}]}, {"base_span": [834, 835], "annotations": [{"normalized_text": "&", "lemma": "&", "root": "&", "root_tokens": ["&"], "ending": "0", "clitic": "", "form": "", "partofspeech": "J"}]}, {"base_span": [835, 837], "annotations": [{"normalized_text": "lt", "lemma": "lt", "root": "lt", "root_tokens": ["lt"], "ending": "0", "clitic": "", "form": "?", "partofspeech": "Y"}]}, {"base_span": [837, 838], "annotations": [{"normalized_text": ";", "lemma": ";", "root": ";", "root_tokens": [";"], "ending": "", "clitic": "", "form": "", "partofspeech": "Z"}]}, {"base_span": [838, 845], "annotations": [{"normalized_text": "allkiri", "lemma": "allkiri", "root": "all_kiri", "root_tokens": ["all", "kiri"], "ending": "0", "clitic": "", "form": "sg n", "partofspeech": "S"}]}, {"base_span": [845, 846], "annotations": [{"normalized_text": "&", "lemma": "&", "root": "&", "root_tokens": ["&"], "ending": "0", "clitic": "", "form": "", "partofspeech": "J"}]}, {"base_span": [846, 848], "annotations": [{"normalized_text": "gt", "lemma": "gt", "root": "gt", "root_tokens": ["gt"], "ending": "0", "clitic": "", "form": "?", "partofspeech": "Y"}]}, {"base_span": [848, 849], "annotations": [{"normalized_text": ";", "lemma": ";", "root": ";", "root_tokens": [";"], "ending": "", "clitic": "", "form": "", "partofspeech": "Z"}]}]}, {"name": "ner", "attributes": ["nertag"], "parent": null, "enveloping": "words", "ambiguous": false, "serialisation_module": null, "meta": {}, "spans": [{"base_span": [[0, 5], [6, 12]], "annotations": [{"nertag": "PER"}]}, {"base_span": [[33, 38], [39, 43]], "annotations": [{"nertag": "PER"}]}, {"base_span": [[78, 83]], "annotations": [{"nertag": "LOC"}]}, {"base_span": [[150, 161], [162, 169]], "annotations": [{"nertag": "PER"}]}, {"base_span": [[197, 202]], "annotations": [{"nertag": "LOC"}]}, {"base_span": [[278, 283], [284, 290]], "annotations": [{"nertag": "PER"}]}, {"base_span": [[300, 305]], "annotations": [{"nertag": "LOC"}]}, {"base_span": [[326, 333]], "annotations": [{"nertag": "PER"}]}, {"base_span": [[393, 400], [401, 407]], "annotations": [{"nertag": "PER"}]}, {"base_span": [[515, 520]], "annotations": [{"nertag": "PER"}]}, {"base_span": [[542, 547]], "annotations": [{"nertag": "PER"}]}, {"base_span": [[603, 608]], "annotations": [{"nertag": "PER"}]}, {"base_span": [[614, 619]], "annotations": [{"nertag": "PER"}]}, {"base_span": [[626, 631]], "annotations": [{"nertag": "PER"}]}, {"base_span": [[666, 672]], "annotations": [{"nertag": "ORG"}]}, {"base_span": [[673, 678], [679, 685]], "annotations": [{"nertag": "PER"}]}, {"base_span": [[701, 706], [707, 713]], "annotations": [{"nertag": "PER"}]}, {"base_span": [[729, 731], [732, 737]], "annotations": [{"nertag": "ORG"}]}, {"base_span": [[824, 825], [826, 833]], "annotations": [{"nertag": "PER"}]}]}, {"name": "sentences", "attributes": [], "parent": null, "enveloping": "words", "ambiguous": false, "serialisation_module": null, "meta": {}, "spans": [{"base_span": [[0, 5], [6, 12], [13, 15], [16, 20], [21, 25], [26, 32], [33, 38], [39, 43], [44, 49], [50, 53], [54, 59], [60, 68], [69, 77], [77, 78], [78, 83], [84, 89], [90, 93], [94, 98], [99, 101], [102, 105], [106, 110], [111, 112], [112, 113], [113, 114], [115, 118], [119, 126], [127, 135], [136, 140], [141, 149], [150, 161], [162, 169], [169, 170], [171, 174], [175, 178], [179, 187], [188, 190], [191, 195], [196, 197], [197, 202], [202, 203], [204, 208], [209, 213], [214, 218], [219, 227], [228, 230], [231, 236], [237, 247], [248, 252], [253, 257], [258, 263], [264, 268], [269, 273], [274, 277], [278, 283], [284, 290], [291, 293], [294, 299], [300, 305], [306, 312], [313, 317], [318, 325], [326, 333], [334, 337], [338, 341], [341, 342]], "annotations": [{}]}, {"base_span": [[343, 347], [348, 354], [355, 360], [361, 366], [367, 371], [372, 376], [377, 383], [384, 386], [387, 392], [393, 400], [401, 407], [408, 409], [410, 414], [415, 417], [418, 419], [420, 426], [427, 429], [430, 431], [432, 437], [438, 444], [445, 449], [450, 457], [458, 461], [462, 467], [468, 480], [481, 485], [486, 497], [497, 498]], "annotations": [{}]}, {"base_span": [[498, 503], [504, 509], [510, 514], [515, 520], [521, 527], [528, 532], [533, 536], [537, 541], [542, 547], [548, 556], [557, 563], [564, 570], [571, 573], [574, 578], [579, 584], [585, 590], [591, 595], [596, 601], [601, 602]], "annotations": [{}]}, {"base_span": [[603, 608], [609, 613], [614, 619], [620, 625], [626, 631], [632, 641], [642, 644], [645, 654], [655, 662], [663, 665], [666, 672], [672, 673]], "annotations": [{}]}, {"base_span": [[673, 678], [679, 685], [686, 687], [687, 689], [689, 690], [690, 697], [697, 698], [698, 700], [700, 701], [701, 706], [707, 713], [714, 715], [715, 717], [717, 718], [718, 725], [725, 726], [726, 728], [728, 729], [729, 731], [732, 737], [738, 752], [753, 758], [759, 765], [765, 766], [767, 785], [786, 788], [788, 789], [789, 790]], "annotations": [{}]}, {"base_span": [[791, 800], [801, 802], [802, 804], [804, 805], [805, 812], [812, 813], [813, 815], [815, 816], [816, 822], [822, 823], [824, 825], [826, 833], [834, 835], [835, 837], [837, 838], [838, 845], [845, 846], [846, 848], [848, 849]], "annotations": [{}]}]}, {"name": "wordner", "attributes": ["nertag"], "parent": null, "enveloping": "words", "ambiguous": false, "serialisation_module": null, "meta": {}, "spans": [{"base_span": [0, 5], "annotations": [{"nertag": "B-PER"}]}, {"base_span": [6, 12], "annotations": [{"nertag": "I-PER"}]}, {"base_span": [13, 15], "annotations": [{"nertag": "O"}]}, {"base_span": [16, 20], "annotations": [{"nertag": "O"}]}, {"base_span": [21, 25], "annotations": [{"nertag": "O"}]}, {"base_span": [26, 32], "annotations": [{"nertag": "O"}]}, {"base_span": [33, 38], "annotations": [{"nertag": "B-PER"}]}, {"base_span": [39, 43], "annotations": [{"nertag": "I-PER"}]}, {"base_span": [44, 49], "annotations": [{"nertag": "O"}]}, {"base_span": [50, 53], "annotations": [{"nertag": "O"}]}, {"base_span": [54, 59], "annotations": [{"nertag": "O"}]}, {"base_span": [60, 68], "annotations": [{"nertag": "O"}]}, {"base_span": [69, 77], "annotations": [{"nertag": "O"}]}, {"base_span": [77, 78], "annotations": [{"nertag": "O"}]}, {"base_span": [78, 83], "annotations": [{"nertag": "B-LOC"}]}, {"base_span": [84, 89], "annotations": [{"nertag": "O"}]}, {"base_span": [90, 93], "annotations": [{"nertag": "O"}]}, {"base_span": [94, 98], "annotations": [{"nertag": "O"}]}, {"base_span": [99, 101], "annotations": [{"nertag": "O"}]}, {"base_span": [102, 105], "annotations": [{"nertag": "O"}]}, {"base_span": [106, 110], "annotations": [{"nertag": "O"}]}, {"base_span": [111, 112], "annotations": [{"nertag": "O"}]}, {"base_span": [112, 113], "annotations": [{"nertag": "O"}]}, {"base_span": [113, 114], "annotations": [{"nertag": "O"}]}, {"base_span": [115, 118], "annotations": [{"nertag": "O"}]}, {"base_span": [119, 126], "annotations": [{"nertag": "O"}]}, {"base_span": [127, 135], "annotations": [{"nertag": "O"}]}, {"base_span": [136, 140], "annotations": [{"nertag": "O"}]}, {"base_span": [141, 149], "annotations": [{"nertag": "O"}]}, {"base_span": [150, 161], "annotations": [{"nertag": "B-PER"}]}, {"base_span": [162, 169], "annotations": [{"nertag": "I-PER"}]}, {"base_span": [169, 170], "annotations": [{"nertag": "O"}]}, {"base_span": [171, 174], "annotations": [{"nertag": "O"}]}, {"base_span": [175, 178], "annotations": [{"nertag": "O"}]}, {"base_span": [179, 187], "annotations": [{"nertag": "O"}]}, {"base_span": [188, 190], "annotations": [{"nertag": "O"}]}, {"base_span": [191, 195], "annotations": [{"nertag": "O"}]}, {"base_span": [196, 197], "annotations": [{"nertag": "O"}]}, {"base_span": [197, 202], "annotations": [{"nertag": "B-LOC"}]}, {"base_span": [202, 203], "annotations": [{"nertag": "O"}]}, {"base_span": [204, 208], "annotations": [{"nertag": "O"}]}, {"base_span": [209, 213], "annotations": [{"nertag": "O"}]}, {"base_span": [214, 218], "annotations": [{"nertag": "O"}]}, {"base_span": [219, 227], "annotations": [{"nertag": "O"}]}, {"base_span": [228, 230], "annotations": [{"nertag": "O"}]}, {"base_span": [231, 236], "annotations": [{"nertag": "O"}]}, {"base_span": [237, 247], "annotations": [{"nertag": "O"}]}, {"base_span": [248, 252], "annotations": [{"nertag": "O"}]}, {"base_span": [253, 257], "annotations": [{"nertag": "O"}]}, {"base_span": [258, 263], "annotations": [{"nertag": "O"}]}, {"base_span": [264, 268], "annotations": [{"nertag": "O"}]}, {"base_span": [269, 273], "annotations": [{"nertag": "O"}]}, {"base_span": [274, 277], "annotations": [{"nertag": "O"}]}, {"base_span": [278, 283], "annotations": [{"nertag": "B-PER"}]}, {"base_span": [284, 290], "annotations": [{"nertag": "I-PER"}]}, {"base_span": [291, 293], "annotations": [{"nertag": "O"}]}, {"base_span": [294, 299], "annotations": [{"nertag": "O"}]}, {"base_span": [300, 305], "annotations": [{"nertag": "B-LOC"}]}, {"base_span": [306, 312], "annotations": [{"nertag": "O"}]}, {"base_span": [313, 317], "annotations": [{"nertag": "O"}]}, {"base_span": [318, 325], "annotations": [{"nertag": "O"}]}, {"base_span": [326, 333], "annotations": [{"nertag": "B-PER"}]}, {"base_span": [334, 337], "annotations": [{"nertag": "O"}]}, {"base_span": [338, 341], "annotations": [{"nertag": "O"}]}, {"base_span": [341, 342], "annotations": [{"nertag": "O"}]}, {"base_span": [343, 347], "annotations": [{"nertag": "O"}]}, {"base_span": [348, 354], "annotations": [{"nertag": "O"}]}, {"base_span": [355, 360], "annotations": [{"nertag": "O"}]}, {"base_span": [361, 366], "annotations": [{"nertag": "O"}]}, {"base_span": [367, 371], "annotations": [{"nertag": "O"}]}, {"base_span": [372, 376], "annotations": [{"nertag": "O"}]}, {"base_span": [377, 383], "annotations": [{"nertag": "O"}]}, {"base_span": [384, 386], "annotations": [{"nertag": "O"}]}, {"base_span": [387, 392], "annotations": [{"nertag": "O"}]}, {"base_span": [393, 400], "annotations": [{"nertag": "B-PER"}]}, {"base_span": [401, 407], "annotations": [{"nertag": "I-PER"}]}, {"base_span": [408, 409], "annotations": [{"nertag": "O"}]}, {"base_span": [410, 414], "annotations": [{"nertag": "O"}]}, {"base_span": [415, 417], "annotations": [{"nertag": "O"}]}, {"base_span": [418, 419], "annotations": [{"nertag": "O"}]}, {"base_span": [420, 426], "annotations": [{"nertag": "O"}]}, {"base_span": [427, 429], "annotations": [{"nertag": "O"}]}, {"base_span": [430, 431], "annotations": [{"nertag": "O"}]}, {"base_span": [432, 437], "annotations": [{"nertag": "O"}]}, {"base_span": [438, 444], "annotations": [{"nertag": "O"}]}, {"base_span": [445, 449], "annotations": [{"nertag": "O"}]}, {"base_span": [450, 457], "annotations": [{"nertag": "O"}]}, {"base_span": [458, 461], "annotations": [{"nertag": "O"}]}, {"base_span": [462, 467], "annotations": [{"nertag": "O"}]}, {"base_span": [468, 480], "annotations": [{"nertag": "O"}]}, {"base_span": [481, 485], "annotations": [{"nertag": "O"}]}, {"base_span": [486, 497], "annotations": [{"nertag": "O"}]}, {"base_span": [497, 498], "annotations": [{"nertag": "O"}]}, {"base_span": [498, 503], "annotations": [{"nertag": "O"}]}, {"base_span": [504, 509], "annotations": [{"nertag": "O"}]}, {"base_span": [510, 514], "annotations": [{"nertag": "O"}]}, {"base_span": [515, 520], "annotations": [{"nertag": "B-PER"}]}, {"base_span": [521, 527], "annotations": [{"nertag": "O"}]}, {"base_span": [528, 532], "annotations": [{"nertag": "O"}]}, {"base_span": [533, 536], "annotations": [{"nertag": "O"}]}, {"base_span": [537, 541], "annotations": [{"nertag": "O"}]}, {"base_span": [542, 547], "annotations": [{"nertag": "B-PER"}]}, {"base_span": [548, 556], "annotations": [{"nertag": "O"}]}, {"base_span": [557, 563], "annotations": [{"nertag": "O"}]}, {"base_span": [564, 570], "annotations": [{"nertag": "O"}]}, {"base_span": [571, 573], "annotations": [{"nertag": "O"}]}, {"base_span": [574, 578], "annotations": [{"nertag": "O"}]}, {"base_span": [579, 584], "annotations": [{"nertag": "O"}]}, {"base_span": [585, 590], "annotations": [{"nertag": "O"}]}, {"base_span": [591, 595], "annotations": [{"nertag": "O"}]}, {"base_span": [596, 601], "annotations": [{"nertag": "O"}]}, {"base_span": [601, 602], "annotations": [{"nertag": "O"}]}, {"base_span": [603, 608], "annotations": [{"nertag": "B-PER"}]}, {"base_span": [609, 613], "annotations": [{"nertag": "O"}]}, {"base_span": [614, 619], "annotations": [{"nertag": "B-PER"}]}, {"base_span": [620, 625], "annotations": [{"nertag": "O"}]}, {"base_span": [626, 631], "annotations": [{"nertag": "B-PER"}]}, {"base_span": [632, 641], "annotations": [{"nertag": "O"}]}, {"base_span": [642, 644], "annotations": [{"nertag": "O"}]}, {"base_span": [645, 654], "annotations": [{"nertag": "O"}]}, {"base_span": [655, 662], "annotations": [{"nertag": "O"}]}, {"base_span": [663, 665], "annotations": [{"nertag": "O"}]}, {"base_span": [666, 672], "annotations": [{"nertag": "B-ORG"}]}, {"base_span": [672, 673], "annotations": [{"nertag": "O"}]}, {"base_span": [673, 678], "annotations": [{"nertag": "B-PER"}]}, {"base_span": [679, 685], "annotations": [{"nertag": "I-PER"}]}, {"base_span": [686, 687], "annotations": [{"nertag": "O"}]}, {"base_span": [687, 689], "annotations": [{"nertag": "O"}]}, {"base_span": [689, 690], "annotations": [{"nertag": "O"}]}, {"base_span": [690, 697], "annotations": [{"nertag": "O"}]}, {"base_span": [697, 698], "annotations": [{"nertag": "O"}]}, {"base_span": [698, 700], "annotations": [{"nertag": "O"}]}, {"base_span": [700, 701], "annotations": [{"nertag": "O"}]}, {"base_span": [701, 706], "annotations": [{"nertag": "B-PER"}]}, {"base_span": [707, 713], "annotations": [{"nertag": "I-PER"}]}, {"base_span": [714, 715], "annotations": [{"nertag": "O"}]}, {"base_span": [715, 717], "annotations": [{"nertag": "O"}]}, {"base_span": [717, 718], "annotations": [{"nertag": "O"}]}, {"base_span": [718, 725], "annotations": [{"nertag": "O"}]}, {"base_span": [725, 726], "annotations": [{"nertag": "O"}]}, {"base_span": [726, 728], "annotations": [{"nertag": "O"}]}, {"base_span": [728, 729], "annotations": [{"nertag": "O"}]}, {"base_span": [729, 731], "annotations": [{"nertag": "B-ORG"}]}, {"base_span": [732, 737], "annotations": [{"nertag": "I-ORG"}]}, {"base_span": [738, 752], "annotations": [{"nertag": "O"}]}, {"base_span": [753, 758], "annotations": [{"nertag": "O"}]}, {"base_span": [759, 765], "annotations": [{"nertag": "O"}]}, {"base_span": [765, 766], "annotations": [{"nertag": "O"}]}, {"base_span": [767, 785], "annotations": [{"nertag": "O"}]}, {"base_span": [786, 788], "annotations": [{"nertag": "O"}]}, {"base_span": [788, 789], "annotations": [{"nertag": "O"}]}, {"base_span": [789, 790], "annotations": [{"nertag": "O"}]}, {"base_span": [791, 800], "annotations": [{"nertag": "O"}]}, {"base_span": [801, 802], "annotations": [{"nertag": "O"}]}, {"base_span": [802, 804], "annotations": [{"nertag": "O"}]}, {"base_span": [804, 805], "annotations": [{"nertag": "O"}]}, {"base_span": [805, 812], "annotations": [{"nertag": "O"}]}, {"base_span": [812, 813], "annotations": [{"nertag": "O"}]}, {"base_span": [813, 815], "annotations": [{"nertag": "O"}]}, {"base_span": [815, 816], "annotations": [{"nertag": "O"}]}, {"base_span": [816, 822], "annotations": [{"nertag": "O"}]}, {"base_span": [822, 823], "annotations": [{"nertag": "O"}]}, {"base_span": [824, 825], "annotations": [{"nertag": "B-PER"}]}, {"base_span": [826, 833], "annotations": [{"nertag": "I-PER"}]}, {"base_span": [834, 835], "annotations": [{"nertag": "O"}]}, {"base_span": [835, 837], "annotations": [{"nertag": "O"}]}, {"base_span": [837, 838], "annotations": [{"nertag": "O"}]}, {"base_span": [838, 845], "annotations": [{"nertag": "O"}]}, {"base_span": [845, 846], "annotations": [{"nertag": "O"}]}, {"base_span": [846, 848], "annotations": [{"nertag": "O"}]}, {"base_span": [848, 849], "annotations": [{"nertag": "O"}]}]}]}